colorprint/__init__.py
colorprint/core.py
colorprint/print_color.py
eldar_colorprint_matrix-0.0.1.dist-info/licenses/LICENSE
eldar_colorprint_matrix-0.0.1.dist-info/METADATA
eldar_colorprint_matrix-0.0.1.dist-info/WHEEL
eldar_colorprint_matrix-0.0.1.dist-info/top_level.txt
eldar_colorprint_matrix-0.0.1.dist-info/RECORD
