Metadata-Version: 2.4
Name: eldar-colorprint-matrix
Version: 0.0.1
Summary: A simple Python library for colorful terminal text output
Home-page: https://github.com/eldar/colorprint
Author: Eldar
Author-email: eldar@example.com
Classifier: Programming Language :: Python :: 3
Classifier: License :: OSI Approved :: MIT License
Classifier: Operating System :: OS Independent
Requires-Python: >=3.8
License-File: LICENSE
Dynamic: author
Dynamic: author-email
Dynamic: classifier
Dynamic: description
Dynamic: description-content-type
Dynamic: home-page
Dynamic: license-file
Dynamic: requires-python
Dynamic: summary
